flashscore_scraper/__init__.py
flashscore_scraper/exceptions.py
flashscore_scraper/core/__init__.py
flashscore_scraper/core/browser.py
flashscore_scraper/core/database.py
flashscore_scraper/models/__init__.py
flashscore_scraper/models/base.py
flashscore_scraper/scrapers/__init__.py
flashscore_scraper/scrapers/base.py
flashscore_scraper/scrapers/flexible_scraper.py
flashscore_scraper/scrapers/match_data_scraper.py
flashscore_scraper/scrapers/match_id_scraper.py
flashscore_scraper/scrapers/odds_data_scraper.py
flashscore_scraper-0.1.0.dist-info/METADATA
flashscore_scraper-0.1.0.dist-info/WHEEL
flashscore_scraper-0.1.0.dist-info/licenses/LICENSE
flashscore_scraper-0.1.0.dist-info/RECORD
