Metadata-Version: 2.4
Name: flashscore-scraper
Version: 0.1.0
Summary: A Python package for scraping handball match data from Flashscore
Project-URL: Repository, https://github.com/bjoernaagaard/flashscore-scraper
Project-URL: Issues, https://github.com/bjoernaagaard/flashscore-scraper/issues
Author-email: Bjørn Aagaard <aagaard@gmail.com>
License-Expression: MIT
License-File: LICENSE
Keywords: betting,flashscore,handball,odds,scraping,sports
Classifier: Development Status :: 4 - Beta
Classifier: Intended Audience :: Developers
Classifier: License :: OSI Approved :: MIT License
Classifier: Programming Language :: Python :: 3
Classifier: Programming Language :: Python :: 3.10
Classifier: Programming Language :: Python :: 3.11
Classifier: Programming Language :: Python :: 3.12
Classifier: Topic :: Internet :: WWW/HTTP :: Dynamic Content
Classifier: Topic :: Software Development :: Libraries :: Application Frameworks
Classifier: Topic :: Software Development :: Libraries :: Python Modules
Requires-Python: >=3.10
Requires-Dist: beautifulsoup4>=4.9.3
Requires-Dist: pydantic>=2.10.6
Requires-Dist: pyyaml>=6.0.1
Requires-Dist: ratelimit>=2.2.1
Requires-Dist: selenium>=4.0.0
Requires-Dist: tqdm>=4.65.0
Requires-Dist: webdriver-manager>=3.8.0
Provides-Extra: dev
Requires-Dist: black>=23.0.0; extra == 'dev'
Requires-Dist: isort>=5.0.0; extra == 'dev'
Requires-Dist: mypy>=1.0.0; extra == 'dev'
Requires-Dist: pytest-cov>=4.0.0; extra == 'dev'
Requires-Dist: pytest>=7.0.0; extra == 'dev'
Requires-Dist: ruff>=0.1.0; extra == 'dev'
